Workbook
Name data: Budget!$A$1:$F$12

Sheet Dashboard
A1: MONTHLY POCKET MONEY ANALYZER & DASHBOARD
A2: Select Analysis Month: | B2: 46023 | D2: Academic Year: 2026 | G2: Currency: ₹ (INR) | J2: Dynamic Pocket Money Analytics • Real-Time Modeling
A3: TOTAL INCOME | D3: TOTAL EXPENSES | G3: NET SAVINGS | J3: SAVINGS RATE | M3: BUDGET REMAINING
A4: =SUMIFS(Transactions!$F:$F,Transactions!$C:$C,"Income",Transactions!$A:$A,">="&$B$2,Transactions!$A:$A,"<"&EDATE($B$2,1)) -> 4035 | D4: =SUMIFS(Transactions!$F:$F,Transactions!$C:$C,"Expense",Transactions!$A:$A,">="&$B$2,Transactions!$A:$A,"<"&EDATE($B$2,1)) -> 3887 | G4: =A4-D4 -> 148 | J4: =IFERROR(G4/A4,0) -> 0.036679058 | M4: =Budget!$D$13 -> 3113
A5: Monthly Pocket Money & Inflows | D5: Total Outflows across all categories | G5: Surplus / Retained Cash | J5: Target Benchmark: ≥ 20.0% | M5: Unspent Monthly Budget
A7: MONTHLY BUDGET VS ACTUAL EXPENSE BREAKDOWN | H7: BUDGET VS ACTUAL SPENDING BY CATEGORY
A8: Category | B8: Monthly Budget | C8: Actual Spending | D8: Remaining | E8: Usage (%) | F8: Status
A9: =Budget!A2 -> Food | B9: =Budget!B2 -> 1800 | C9: =Budget!C2 -> 1285 | D9: =Budget!D2 -> 515 | E9: =Budget!E2 -> 0.71388889 | F9: =Budget!F2 -> Within Budget
A10: =Budget!A3 -> Travel | B10: =Budget!B3 -> 800 | C10: =Budget!C3 -> 390 | D10: =Budget!D3 -> 410 | E10: =Budget!E3 -> 0.4875 | F10: =Budget!F3 -> Within Budget
A11: =Budget!A4 -> Stationery | B11: =Budget!B4 -> 500 | C11: =Budget!C4 -> 180 | D11: =Budget!D4 -> 320 | E11: =Budget!E4 -> 0.36 | F11: =Budget!F4 -> Within Budget
A12: =Budget!A5 -> Education | B12: =Budget!B5 -> 600 | C12: =Budget!C5 -> 255 | D12: =Budget!D5 -> 345 | E12: =Budget!E5 -> 0.425 | F12: =Budget!F5 -> Within Budget
A13: =Budget!A6 -> Entertainment | B13: =Budget!B6 -> 700 | C13: =Budget!C6 -> 568 | D13: =Budget!D6 -> 132 | E13: =Budget!E6 -> 0.81142857 | F13: =Budget!F6 -> Near Limit
A14: =Budget!A7 -> Mobile | B14: =Budget!B7 -> 300 | C14: =Budget!C7 -> 239 | D14: =Budget!D7 -> 61 | E14: =Budget!E7 -> 0.79666667 | F14: =Budget!F7 -> Within Budget
A15: =Budget!A8 -> Shopping | B15: =Budget!B8 -> 1000 | C15: =Budget!C8 -> 750 | D15: =Budget!D8 -> 250 | E15: =Budget!E8 -> 0.75 | F15: =Budget!F8 -> Within Budget
A16: =Budget!A9 -> Personal Care | B16: =Budget!B9 -> 400 | C16: =Budget!C9 -> 220 | D16: =Budget!D9 -> 180 | E16: =Budget!E9 -> 0.55 | F16: =Budget!F9 -> Within Budget
A17: =Budget!A10 -> Health | B17: =Budget!B10 -> 300 | C17: =Budget!C10 -> 0 | D17: =Budget!D10 -> 300 | E17: =Budget!E10 -> 0 | F17: =Budget!F10 -> Within Budget
A18: =Budget!A11 -> Gifts | B18: =Budget!B11 -> 300 | C18: =Budget!C11 -> 0 | D18: =Budget!D11 -> 300 | E18: =Budget!E11 -> 0 | F18: =Budget!F11 -> Within Budget
A19: =Budget!A12 -> Other | B19: =Budget!B12 -> 300 | C19: =Budget!C12 -> 0 | D19: =Budget!D12 -> 300 | E19: =Budget!E12 -> 0 | F19: =Budget!F12 -> Within Budget
A20: Total | B20: =SUM(B9:B19) -> 7000 | C20: =SUM(C9:C19) -> 3887 | D20: =B20-C20 -> 3113 | E20: =IFERROR(C20/B20,0) -> 0.55528571 | F20: =IF(C20>B20,"Over Budget",IF(C20>=B20*0.8,"Near Limit","Within Budget")) -> Within Budget
A22: 12-MONTH FINANCIAL TREND (INCOME vs EXPENSE vs SAVINGS) | H22: EXPENSE DISTRIBUTION BY CATEGORY (% SHARE)
A38: KEY MONTHLY FINANCIAL INSIGHTS & BUDGET HEALTH
A39: TOP EXPENSE CATEGORY | D39: MAX SINGLE TRANSACTION | G39: AVERAGE DAILY SPEND | J39: BUDGET ADHERENCE | M39: TOTAL TRANSACTIONS
A40: =INDEX(A9:A19, MATCH(MAX(C9:C19), C9:C19, 0)) & " (" & TEXT(MAX(C9:C19), "₹#,##0") & ")" -> Food (₹1,285) | D40: =_xlfn.MAXIFS(Transactions!$F:$F, Transactions!$C:$C, "Expense", Transactions!$A:$A, ">="&$B$2, Transactions!$A:$A, "<"&EDATE($B$2,1)) -> 450 | G40: =D4/DAY(EOMONTH($B$2,0)) -> 125.3871 | J40: =COUNTIF(F9:F19,"Within Budget") & " of 11 within limit" -> 10 of 11 within limit | M40: =COUNTIFS(Transactions!$A:$A,">="&$B$2,Transactions!$A:$A,"<"&EDATE($B$2,1)) -> 30
A42: ="Financial Health Summary: " & IF(J4>=0.2,"Outstanding savings discipline! You saved " & TEXT(J4,"0.0%") & " of your pocket money, comfortably surpassing the 20% savings target. Keep allocating surplus into your Savings Goals.", IF(J4>0,"Positive cash balance maintained (" & TEXT(J4,"0.0%") & " saved). Look into categories marked 'Near Limit' or 'Over Budget' to reduce discretionary spend and reach 20% savings.", "Warning: Expenses exceeded income this month (Deficit: " & TEXT(ABS(G4),"₹#,##0") & "). Immediate spending reductions required in high-variance categories.")) -> Financial Health Summary: Positive cash balance maintained (3.7% saved). Look into categories marked 'Near Limit' or 'Over Budget' to reduce discretionary spend and reach 20% savings.

Sheet Transactions
A1: Date | B1: Transaction ID | C1: Type | D1: Category | E1: Description | F1: Amount | G1: Payment Method | H1: Month | I1: Running Balance | J1: Budget Status
A2: 46023 | B2: TX001 | C2: Income | D2: Pocket Money | E2: Monthly allowance from parents | F2: 3000 | G2: UPI | H2: =TEXT(A2,"mmm-yyyy") -> Jan-2026 | I2: =SUMIFS($F$2:F2,$C$2:C2,"Income")-SUMIFS($F$2:F2,$C$2:C2,"Expense") -> 3000 | J2: =IF(C2="Income","-",IFERROR(VLOOKUP(D2,Budget!$A$2:$F$12,6,FALSE),"-")) -> -
A3: 46024 | B3: TX002 | C3: Expense | D3: Food | E3: Breakfast and snacks | F3: 85 | G3: UPI | H3: =TEXT(A3,"mmm-yyyy") -> Jan-2026 | I3: =SUMIFS($F$2:F3,$C$2:C3,"Income")-SUMIFS($F$2:F3,$C$2:C3,"Expense") -> 2915 | J3: =IF(C3="Income","-",IFERROR(VLOOKUP(D3,Budget!$A$2:$F$12,6,FALSE),"-")) -> Within Budget
A4: 46025 | B4: TX003 | C4: Expense | D4: Travel | E4: Bus fare | F4: 40 | G4: Cash | H4: =TEXT(A4,"mmm-yyyy") -> Jan-2026 | I4: =SUMIFS($F$2:F4,$C$2:C4,"Income")-SUMIFS($F$2:F4,$C$2:C4,"Expense") -> 2875 | J4: =IF(C4="Income","-",IFERROR(VLOOKUP(D4,Budget!$A$2:$F$12,6,FALSE),"-")) -> Within Budget
A5: 46026 | B5: TX004 | C5: Expense | D5: Food | E5: Lunch at college | F5: 120 | G5: UPI | H5: =TEXT(A5,"mmm-yyyy") -> Jan-2026 | I5: =SUMIFS($F$2:F5,$C$2:C5,"Income")-SUMIFS($F$2:F5,$C$2:C5,"Expense") -> 2755 | J5: =IF(C5="Income","-",IFERROR(VLOOKUP(D5,Budget!$A$2:$F$12,6,FALSE),"-")) -> Within Budget
A6: 46027 | B6: TX005 | C6: Expense | D6: Stationery | E6: Notebooks and pens | F6: 180 | G6: UPI | H6: =TEXT(A6,"mmm-yyyy") -> Jan-2026 | I6: =SUMIFS($F$2:F6,$C$2:C6,"Income")-SUMIFS($F$2:F6,$C$2:C6,"Expense") -> 2575 | J6: =IF(C6="Income","-",IFERROR(VLOOKUP(D6,Budget!$A$2:$F$12,6,FALSE),"-")) -> Within Budget
A7: 46028 | B7: TX006 | C7: Expense | D7: Entertainment | E7: Movie ticket | F7: 250 | G7: UPI | H7: =TEXT(A7,"mmm-yyyy") -> Jan-2026 | I7: =SUMIFS($F$2:F7,$C$2:C7,"Income")-SUMIFS($F$2:F7,$C$2:C7,"Expense") -> 2325 | J7: =IF(C7="Income","-",IFERROR(VLOOKUP(D7,Budget!$A$2:$F$12,6,FALSE),"-")) -> Near Limit
A8: 46029 | B8: TX007 | C8: Income | D8: Gift | E8: Money received from relative | F8: 500 | G8: Cash | H8: =TEXT(A8,"mmm-yyyy") -> Jan-2026 | I8: =SUMIFS($F$2:F8,$C$2:C8,"Income")-SUMIFS($F$2:F8,$C$2:C8,"Expense") -> 2825 | J8: =IF(C8="Income","-",IFERROR(VLOOKUP(D8,Budget!$A$2:$F$12,6,FALSE),"-")) -> -
A9: 46030 | B9: TX008 | C9: Expense | D9: Food | E9: Snacks with friends | F9: 110 | G9: Cash | H9: =TEXT(A9,"mmm-yyyy") -> Jan-2026 | I9: =SUMIFS($F$2:F9,$C$2:C9,"Income")-SUMIFS($F$2:F9,$C$2:C9,"Expense") -> 2715 | J9: =IF(C9="Income","-",IFERROR(VLOOKUP(D9,Budget!$A$2:$F$12,6,FALSE),"-")) -> Within Budget
A10: 46031 | B10: TX009 | C10: Expense | D10: Travel | E10: Auto fare | F10: 90 | G10: UPI | H10: =TEXT(A10,"mmm-yyyy") -> Jan-2026 | I10: =SUMIFS($F$2:F10,$C$2:C10,"Income")-SUMIFS($F$2:F10,$C$2:C10,"Expense") -> 2625 | J10: =IF(C10="Income","-",IFERROR(VLOOKUP(D10,Budget!$A$2:$F$12,6,FALSE),"-")) -> Within Budget
A11: 46032 | B11: TX010 | C11: Expense | D11: Mobile | E11: Mobile recharge | F11: 239 | G11: UPI | H11: =TEXT(A11,"mmm-yyyy") -> Jan-2026 | I11: =SUMIFS($F$2:F11,$C$2:C11,"Income")-SUMIFS($F$2:F11,$C$2:C11,"Expense") -> 2386 | J11: =IF(C11="Income","-",IFERROR(VLOOKUP(D11,Budget!$A$2:$F$12,6,FALSE),"-")) -> Within Budget
A12: 46033 | B12: TX011 | C12: Expense | D12: Food | E12: Dinner | F12: 160 | G12: UPI | H12: =TEXT(A12,"mmm-yyyy") -> Jan-2026 | I12: =SUMIFS($F$2:F12,$C$2:C12,"Income")-SUMIFS($F$2:F12,$C$2:C12,"Expense") -> 2226 | J12: =IF(C12="Income","-",IFERROR(VLOOKUP(D12,Budget!$A$2:$F$12,6,FALSE),"-")) -> Within Budget
A13: 46034 | B13: TX012 | C13: Expense | D13: Shopping | E13: T-shirt | F13: 450 | G13: UPI | H13: =TEXT(A13,"mmm-yyyy") -> Jan-2026 | I13: =SUMIFS($F$2:F13,$C$2:C13,"Income")-SUMIFS($F$2:F13,$C$2:C13,"Expense") -> 1776 | J13: =IF(C13="Income","-",IFERROR(VLOOKUP(D13,Budget!$A$2:$F$12,6,FALSE),"-")) -> Within Budget
... A60: 46090 | B60: TX059 | C60: Expense | D60: Food | E60: Snacks with friends | F60: 120 | G60: Cash | H60: =TEXT(A60,"mmm-yyyy") -> Mar-2026 | I60: =SUMIFS($F$2:F60,$C$2:C60,"Income")-SUMIFS($F$2:F60,$C$2:C60,"Expense") -> 3075 | J60: =IF(C60="Income","-",IFERROR(VLOOKUP(D60,Budget!$A$2:$F$12,6,FALSE),"-")) -> Within Budget
A61: 46091 | B61: TX060 | C61: Expense | D61: Mobile | E61: Mobile recharge | F61: 239 | G61: UPI | H61: =TEXT(A61,"mmm-yyyy") -> Mar-2026 | I61: =SUMIFS($F$2:F171,$C$2:C171,"Income")-SUMIFS($F$2:F171,$C$2:C171,"Expense") -> 1735 | J61: =IF(C61="Income","-",IFERROR(VLOOKUP(D61,Budget!$A$2:$F$12,6,FALSE),"-")) -> Within Budget
A62: 46092 | B62: TX061 | C62: Expense | D62: Travel | E62: Bus and auto fare | F62: 80 | G62: UPI | H62: =TEXT(A62,"mmm-yyyy") -> Mar-2026 | I62: =SUMIFS($F$2:F171,$C$2:C171,"Income")-SUMIFS($F$2:F171,$C$2:C171,"Expense") -> 1735 | J62: =IF(C62="Income","-",IFERROR(VLOOKUP(D62,Budget!$A$2:$F$12,6,FALSE),"-")) -> Within Budget
A63: 46093 | B63: TX062 | C63: Expense | D63: Food | E63: College canteen lunch | F63: 130 | G63: UPI | H63: =TEXT(A63,"mmm-yyyy") -> Mar-2026 | I63: =SUMIFS($F$2:F171,$C$2:C171,"Income")-SUMIFS($F$2:F171,$C$2:C171,"Expense") -> 1735 | J63: =IF(C63="Income","-",IFERROR(VLOOKUP(D63,Budget!$A$2:$F$12,6,FALSE),"-")) -> Within Budget
A64: 46094 | B64: TX063 | C64: Expense | D64: Stationery | E64: Highlighters and sticky notes | F64: 110 | G64: Cash | H64: =TEXT(A64,"mmm-yyyy") -> Mar-2026 | I64: =SUMIFS($F$2:F171,$C$2:C171,"Income")-SUMIFS($F$2:F171,$C$2:C171,"Expense") -> 1735 | J64: =IF(C64="Income","-",IFERROR(VLOOKUP(D64,Budget!$A$2:$F$12,6,FALSE),"-")) -> Within Budget
A65: 46095 | B65: TX064 | C65: Expense | D65: Food | E65: Evening snacks with friends | F65: 95 | G65: Cash | H65: =TEXT(A65,"mmm-yyyy") -> Mar-2026 | I65: =SUMIFS($F$2:F171,$C$2:C171,"Income")-SUMIFS($F$2:F171,$C$2:C171,"Expense") -> 1735 | J65: =IF(C65="Income","-",IFERROR(VLOOKUP(D65,Budget!$A$2:$F$12,6,FALSE),"-")) -> Within Budget
A66: 46096 | B66: TX065 | C66: Income | D66: Pocket Money | E66: Mid-month allowance bonus | F66: 500 | G66: UPI | H66: =TEXT(A66,"mmm-yyyy") -> Mar-2026 | I66: =SUMIFS($F$2:F171,$C$2:C171,"Income")-SUMIFS($F$2:F171,$C$2:C171,"Expense") -> 1735 | J66: =IF(C66="Income","-",IFERROR(VLOOKUP(D66,Budget!$A$2:$F$12,6,FALSE),"-")) -> -
A67: 46097 | B67: TX066 | C67: Expense | D67: Travel | E67: Bus fare | F67: 40 | G67: Cash | H67: =TEXT(A67,"mmm-yyyy") -> Mar-2026 | I67: =SUMIFS($F$2:F171,$C$2:C171,"Income")-SUMIFS($F$2:F171,$C$2:C171,"Expense") -> 1735 | J67: =IF(C67="Income","-",IFERROR(VLOOKUP(D67,Budget!$A$2:$F$12,6,FALSE),"-")) -> Within Budget
A68: 46098 | B68: TX067 | C68: Expense | D68: Food | E68: Lunch at cafe | F68: 160 | G68: UPI | H68: =TEXT(A68,"mmm-yyyy") -> Mar-2026 | I68: =SUMIFS($F$2:F171,$C$2:C171,"Income")-SUMIFS($F$2:F171,$C$2:C171,"Expense") -> 1735 | J68: =IF(C68="Income","-",IFERROR(VLOOKUP(D68,Budget!$A$2:$F$12,6,FALSE),"-")) -> Within Budget
A69: 46099 | B69: TX068 | C69: Expense | D69: Education | E69: Sem exam photocopying & bind | F69: 120 | G69: Cash | H69: =TEXT(A69,"mmm-yyyy") -> Mar-2026 | I69: =SUMIFS($F$2:F171,$C$2:C171,"Income")-SUMIFS($F$2:F171,$C$2:C171,"Expense") -> 1735 | J69: =IF(C69="Income","-",IFERROR(VLOOKUP(D69,Budget!$A$2:$F$12,6,FALSE),"-")) -> Within Budget
A70: 46100 | B70: TX069 | C70: Expense | D70: Personal Care | E70: Skincare & toiletries | F70: 190 | G70: UPI | H70: =TEXT(A70,"mmm-yyyy") -> Mar-2026 | I70: =SUMIFS($F$2:F171,$C$2:C171,"Income")-SUMIFS($F$2:F171,$C$2:C171,"Expense") -> 1735 | J70: =IF(C70="Income","-",IFERROR(VLOOKUP(D70,Budget!$A$2:$F$12,6,FALSE),"-")) -> Within Budget
A71: 46101 | B71: TX070 | C71: Expense | D71: Food | E71: Pizza treat with friends | F71: 310 | G71: UPI | H71: =TEXT(A71,"mmm-yyyy") -> Mar-2026 | I71: =SUMIFS($F$2:F171,$C$2:C171,"Income")-SUMIFS($F$2:F171,$C$2:C171,"Expense") -> 1735 | J71: =IF(C71="Income","-",IFERROR(VLOOKUP(D71,Budget!$A$2:$F$12,6,FALSE),"-")) -> Within Budget
A72: 46102 | B72: TX071 | C72: Expense | D72: Travel | E72: Metro and rickshaw | F72: 70 | G72: UPI | H72: =TEXT(A72,"mmm-yyyy") -> Mar-2026 | I72: =SUMIFS($F$2:F171,$C$2:C171,"Income")-SUMIFS($F$2:F171,$C$2:C171,"Expense") -> 1735 | J72: =IF(C72="Income","-",IFERROR(VLOOKUP(D72,Budget!$A$2:$F$12,6,FALSE),"-")) -> Within Budget
A73: 46103 | B73: TX072 | C73: Expense | D73: Shopping | E73: Book and stationery holder | F73: 250 | G73: UPI | H73: =TEXT(A73,"mmm-yyyy") -> Mar-2026 | I73: =SUMIFS($F$2:F171,$C$2:C171,"Income")-SUMIFS($F$2:F171,$C$2:C171,"Expense") -> 1735 | J73: =IF(C73="Income","-",IFERROR(VLOOKUP(D73,Budget!$A$2:$F$12,6,FALSE),"-")) -> Within Budget
A74: 46104 | B74: TX073 | C74: Expense | D74: Food | E74: Breakfast and juice | F74: 85 | G74: Cash | H74: =TEXT(A74,"mmm-yyyy") -> Mar-2026 | I74: =SUMIFS($F$2:F171,$C$2:C171,"Income")-SUMIFS($F$2:F171,$C$2:C171,"Expense") -> 1735 | J74: =IF(C74="Income","-",IFERROR(VLOOKUP(D74,Budget!$A$2:$F$12,6,FALSE),"-")) -> Within Budget
A75: 46105 | B75: TX074 | C75: Expense | D75: Entertainment | E75: Movie ticket (weekend) | F75: 220 | G75: UPI | H75: =TEXT(A75,"mmm-yyyy") -> Mar-2026 | I75: =SUMIFS($F$2:F171,$C$2:C171,"Income")-SUMIFS($F$2:F171,$C$2:C171,"Expense") -> 1735 | J75: =IF(C75="Income","-",IFERROR(VLOOKUP(D75,Budget!$A$2:$F$12,6,FALSE),"-")) -> Near Limit
A76: 46106 | B76: TX075 | C76: Income | D76: Savings Interest | E76: Quarterly bank interest | F76: 42 | G76: Bank | H76: =TEXT(A76,"mmm-yyyy") -> Mar-2026 | I76: =SUMIFS($F$2:F171,$C$2:C171,"Income")-SUMIFS($F$2:F171,$C$2:C171,"Expense") -> 1735 | J76: =IF(C76="Income","-",IFERROR(VLOOKUP(D76,Budget!$A$2:$F$12,6,FALSE),"-")) -> -
A77: 46107 | B77: TX076 | C77: Expense | D77: Travel | E77: Bus fare | F77: 40 | G77: Cash | H77: =TEXT(A77,"mmm-yyyy") -> Mar-2026 | I77: =SUMIFS($F$2:F171,$C$2:C171,"Income")-SUMIFS($F$2:F171,$C$2:C171,"Expense") -> 1735 | J77: =IF(C77="Income","-",IFERROR(VLOOKUP(D77,Budget!$A$2:$F$12,6,FALSE),"-")) -> Within Budget
A78: 46108 | B78: TX077 | C78: Expense | D78: Health | E78: First aid & pain relief meds | F78: 140 | G78: UPI | H78: =TEXT(A78,"mmm-yyyy") -> Mar-2026 | I78: =SUMIFS($F$2:F171,$C$2:C171,"Income")-SUMIFS($F$2:F171,$C$2:C171,"Expense") -> 1735 | J78: =IF(C78="Income","-",IFERROR(VLOOKUP(D78,Budget!$A$2:$F$12,6,FALSE),"-")) -> Within Budget
A79: 46109 | B79: TX078 | C79: Expense | D79: Food | E79: Dinner with roommates | F79: 180 | G79: UPI | H79: =TEXT(A79,"mmm-yyyy") -> Mar-2026 | I79: =SUMIFS($F$2:F171,$C$2:C171,"Income")-SUMIFS($F$2:F171,$C$2:C171,"Expense") -> 1735 | J79: =IF(C79="Income","-",IFERROR(VLOOKUP(D79,Budget!$A$2:$F$12,6,FALSE),"-")) -> Within Budget
A80: 46110 | B80: TX079 | C80: Expense | D80: Gifts | E80: Friend's birthday gift | F80: 250 | G80: UPI | H80: =TEXT(A80,"mmm-yyyy") -> Mar-2026 | I80: =SUMIFS($F$2:F171,$C$2:C171,"Income")-SUMIFS($F$2:F171,$C$2:C171,"Expense") -> 1735 | J80: =IF(C80="Income","-",IFERROR(VLOOKUP(D80,Budget!$A$2:$F$12,6,FALSE),"-")) -> Within Budget
A81: 46111 | B81: TX080 | C81: Expense | D81: Other | E81: Laundry & dry cleaning | F81: 160 | G81: Cash | H81: =TEXT(A81,"mmm-yyyy") -> Mar-2026 | I81: =SUMIFS($F$2:F171,$C$2:C171,"Income")-SUMIFS($F$2:F171,$C$2:C171,"Expense") -> 1735 | J81: =IF(C81="Income","-",IFERROR(VLOOKUP(D81,Budget!$A$2:$F$12,6,FALSE),"-")) -> Within Budget
A82: 46113 | B82: TX081 | C82: Income | D82: Pocket Money | E82: April monthly allowance | F82: 3200 | G82: UPI | H82: =TEXT(A82,"mmm-yyyy") -> Apr-2026 | I82: =SUMIFS($F$2:F171,$C$2:C171,"Income")-SUMIFS($F$2:F171,$C$2:C171,"Expense") -> 1735 | J82: =IF(C82="Income","-",IFERROR(VLOOKUP(D82,Budget!$A$2:$F$12,6,FALSE),"-")) -> -
A83: 46114 | B83: TX082 | C83: Expense | D83: Food | E83: Breakfast and coffee | F83: 75 | G83: UPI | H83: =TEXT(A83,"mmm-yyyy") -> Apr-2026 | I83: =SUMIFS($F$2:F171,$C$2:C171,"Income")-SUMIFS($F$2:F171,$C$2:C171,"Expense") -> 1735 | J83: =IF(C83="Income","-",IFERROR(VLOOKUP(D83,Budget!$A$2:$F$12,6,FALSE),"-")) -> Within Budget
A84: 46115 | B84: TX083 | C84: Expense | D84: Travel | E84: Monthly bus pass recharge | F84: 450 | G84: UPI | H84: =TEXT(A84,"mmm-yyyy") -> Apr-2026 | I84: =SUMIFS($F$2:F171,$C$2:C171,"Income")-SUMIFS($F$2:F171,$C$2:C171,"Expense") -> 1735 | J84: =IF(C84="Income","-",IFERROR(VLOOKUP(D84,Budget!$A$2:$F$12,6,FALSE),"-")) -> Within Budget
A85: 46116 | B85: TX084 | C85: Expense | D85: Food | E85: College lunch | F85: 120 | G85: UPI | H85: =TEXT(A85,"mmm-yyyy") -> Apr-2026 | I85: =SUMIFS($F$2:F171,$C$2:C171,"Income")-SUMIFS($F$2:F171,$C$2:C171,"Expense") -> 1735 | J85: =IF(C85="Income","-",IFERROR(VLOOKUP(D85,Budget!$A$2:$F$12,6,FALSE),"-")) -> Within Budget
A86: 46117 | B86: TX085 | C86: Expense | D86: Stationery | E86: Exam answer sheets & pens | F86: 150 | G86: Cash | H86: =TEXT(A86,"mmm-yyyy") -> Apr-2026 | I86: =SUMIFS($F$2:F171,$C$2:C171,"Income")-SUMIFS($F$2:F171,$C$2:C171,"Expense") -> 1735 | J86: =IF(C86="Income","-",IFERROR(VLOOKUP(D86,Budget!$A$2:$F$12,6,FALSE),"-")) -> Within Budget
A87: 46118 | B87: TX086 | C87: Expense | D87: Entertainment | E87: Streaming subscription | F87: 199 | G87: UPI | H87: =TEXT(A87,"mmm-yyyy") -> Apr-2026 | I87: =SUMIFS($F$2:F171,$C$2:C171,"Income")-SUMIFS($F$2:F171,$C$2:C171,"Expense") -> 1735 | J87: =IF(C87="Income","-",IFERROR(VLOOKUP(D87,Budget!$A$2:$F$12,6,FALSE),"-")) -> Near Limit
A88: 46119 | B88: TX087 | C88: Income | D88: Part-time Work | E88: Math tutoring sessions | F88: 1000 | G88: UPI | H88: =TEXT(A88,"mmm-yyyy") -> Apr-2026 | I88: =SUMIFS($F$2:F171,$C$2:C171,"Income")-SUMIFS($F$2:F171,$C$2:C171,"Expense") -> 1735 | J88: =IF(C88="Income","-",IFERROR(VLOOKUP(D88,Budget!$A$2:$F$12,6,FALSE),"-")) -> -
A89: 46120 | B89: TX088 | C89: Expense | D89: Food | E89: Dinner at mess/dhaba | F89: 140 | G89: Cash | H89: =TEXT(A89,"mmm-yyyy") -> Apr-2026 | I89: =SUMIFS($F$2:F171,$C$2:C171,"Income")-SUMIFS($F$2:F171,$C$2:C171,"Expense") -> 1735 | J89: =IF(C89="Income","-",IFERROR(VLOOKUP(D89,Budget!$A$2:$F$12,6,FALSE),"-")) -> Within Budget
A90: 46121 | B90: TX089 | C90: Expense | D90: Travel | E90: Auto fare (rainy day) | F90: 90 | G90: Cash | H90: =TEXT(A90,"mmm-yyyy") -> Apr-2026 | I90: =SUMIFS($F$2:F171,$C$2:C171,"Income")-SUMIFS($F$2:F171,$C$2:C171,"Expense") -> 1735 | J90: =IF(C90="Income","-",IFERROR(VLOOKUP(D90,Budget!$A$2:$F$12,6,FALSE),"-")) -> Within Budget
A91: 46122 | B91: TX090 | C91: Expense | D91: Mobile | E91: Monthly prepaid pack | F91: 239 | G91: UPI | H91: =TEXT(A91,"mmm-yyyy") -> Apr-2026 | I91: =SUMIFS($F$2:F171,$C$2:C171,"Income")-SUMIFS($F$2:F171,$C$2:C171,"Expense") -> 1735 | J91: =IF(C91="Income","-",IFERROR(VLOOKUP(D91,Budget!$A$2:$F$12,6,FALSE),"-")) -> Within Budget
A92: 46123 | B92: TX091 | C92: Expense | D92: Shopping | E92: Summer t-shirt | F92: 499 | G92: UPI | H92: =TEXT(A92,"mmm-yyyy") -> Apr-2026 | I92: =SUMIFS($F$2:F171,$C$2:C171,"Income")-SUMIFS($F$2:F171,$C$2:C171,"Expense") -> 1735 | J92: =IF(C92="Income","-",IFERROR(VLOOKUP(D92,Budget!$A$2:$F$12,6,FALSE),"-")) -> Within Budget
A93: 46124 | B93: TX092 | C93: Expense | D93: Food | E93: Snacks and cold beverage | F93: 80 | G93: UPI | H93: =TEXT(A93,"mmm-yyyy") -> Apr-2026 | I93: =SUMIFS($F$2:F171,$C$2:C171,"Income")-SUMIFS($F$2:F171,$C$2:C171,"Expense") -> 1735 | J93: =IF(C93="Income","-",IFERROR(VLOOKUP(D93,Budget!$A$2:$F$12,6,FALSE),"-")) -> Within Budget
A94: 46125 | B94: TX093 | C94: Expense | D94: Education | E94: Project poster printing | F94: 180 | G94: UPI | H94: =TEXT(A94,"mmm-yyyy") -> Apr-2026 | I94: =SUMIFS($F$2:F171,$C$2:C171,"Income")-SUMIFS($F$2:F171,$C$2:C171,"Expense") -> 1735 | J94: =IF(C94="Income","-",IFERROR(VLOOKUP(D94,Budget!$A$2:$F$12,6,FALSE),"-")) -> Within Budget
A95: 46126 | B95: TX094 | C95: Expense | D95: Travel | E95: Metro tokens | F95: 60 | G95: Cash | H95: =TEXT(A95,"mmm-yyyy") -> Apr-2026 | I95: =SUMIFS($F$2:F171,$C$2:C171,"Income")-SUMIFS($F$2:F171,$C$2:C171,"Expense") -> 1735 | J95: =IF(C95="Income","-",IFERROR(VLOOKUP(D95,Budget!$A$2:$F$12,6,FALSE),"-")) -> Within Budget
A96: 46127 | B96: TX095 | C96: Income | D96: Gift | E96: Festival gift from grandparents | F96: 800 | G96: Cash | H96: =TEXT(A96,"mmm-yyyy") -> Apr-2026 | I96: =SUMIFS($F$2:F171,$C$2:C171,"Income")-SUMIFS($F$2:F171,$C$2:C171,"Expense") -> 1735 | J96: =IF(C96="Income","-",IFERROR(VLOOKUP(D96,Budget!$A$2:$F$12,6,FALSE),"-")) -> -
A97: 46128 | B97: TX096 | C97: Expense | D97: Food | E97: Lunch at campus canteen | F97: 130 | G97: UPI | H97: =TEXT(A97,"mmm-yyyy") -> Apr-2026 | I97: =SUMIFS($F$2:F171,$C$2:C171,"Income")-SUMIFS($F$2:F171,$C$2:C171,"Expense") -> 1735 | J97: =IF(C97="Income","-",IFERROR(VLOOKUP(D97,Budget!$A$2:$F$12,6,FALSE),"-")) -> Within Budget
A98: 46129 | B98: TX097 | C98: Expense | D98: Personal Care | E98: Haircut and grooming | F98: 180 | G98: Cash | H98: =TEXT(A98,"mmm-yyyy") -> Apr-2026 | I98: =SUMIFS($F$2:F171,$C$2:C171,"Income")-SUMIFS($F$2:F171,$C$2:C171,"Expense") -> 1735 | J98: =IF(C98="Income","-",IFERROR(VLOOKUP(D98,Budget!$A$2:$F$12,6,FALSE),"-")) -> Within Budget
A99: 46130 | B99: TX098 | C99: Expense | D99: Entertainment | E99: Bowling and snacks | F99: 320 | G99: UPI | H99: =TEXT(A99,"mmm-yyyy") -> Apr-2026 | I99: =SUMIFS($F$2:F171,$C$2:C171,"Income")-SUMIFS($F$2:F171,$C$2:C171,"Expense") -> 1735 | J99: =IF(C99="Income","-",IFERROR(VLOOKUP(D99,Budget!$A$2:$F$12,6,FALSE),"-")) -> Near Limit
A100: 46131 | B100: TX099 | C100: Expense | D100: Food | E100: Ice cream treat with friends | F100: 110 | G100: UPI | H100: =TEXT(A100,"mmm-yyyy") -> Apr-2026 | I100: =SUMIFS($F$2:F171,$C$2:C171,"Income")-SUMIFS($F$2:F171,$C$2:C171,"Expense") -> 1735 | J100: =IF(C100="Income","-",IFERROR(VLOOKUP(D100,Budget!$A$2:$F$12,6,FALSE),"-")) -> Within Budget
A101: 46132 | B101: TX100 | C101: Expense | D101: Health | E101: Multivitamins & eyedrops | F101: 210 | G101: UPI | H101: =TEXT(A101,"mmm-yyyy") -> Apr-2026 | I101: =SUMIFS($F$2:F171,$C$2:C171,"Income")-SUMIFS($F$2:F171,$C$2:C171,"Expense") -> 1735 | J101: =IF(C101="Income","-",IFERROR(VLOOKUP(D101,Budget!$A$2:$F$12,6,FALSE),"-")) -> Within Budget
A102: 46133 | B102: TX101 | C102: Expense | D102: Food | E102: Breakfast and sandwich | F102: 90 | G102: Cash | H102: =TEXT(A102,"mmm-yyyy") -> Apr-2026 | I102: =SUMIFS($F$2:F171,$C$2:C171,"Income")-SUMIFS($F$2:F171,$C$2:C171,"Expense") -> 1735 | J102: =IF(C102="Income","-",IFERROR(VLOOKUP(D102,Budget!$A$2:$F$12,6,FALSE),"-")) -> Within Budget
A103: 46134 | B103: TX102 | C103: Expense | D103: Shopping | E103: Phone case & screen guard | F103: 299 | G103: UPI | H103: =TEXT(A103,"mmm-yyyy") -> Apr-2026 | I103: =SUMIFS($F$2:F171,$C$2:C171,"Income")-SUMIFS($F$2:F171,$C$2:C171,"Expense") -> 1735 | J103: =IF(C103="Income","-",IFERROR(VLOOKUP(D103,Budget!$A$2:$F$12,6,FALSE),"-")) -> Within Budget
A104: 46135 | B104: TX103 | C104: Expense | D104: Travel | E104: Auto fare to library | F104: 70 | G104: Cash | H104: =TEXT(A104,"mmm-yyyy") -> Apr-2026 | I104: =SUMIFS($F$2:F171,$C$2:C171,"Income")-SUMIFS($F$2:F171,$C$2:C171,"Expense") -> 1735 | J104: =IF(C104="Income","-",IFERROR(VLOOKUP(D104,Budget!$A$2:$F$12,6,FALSE),"-")) -> Within Budget
A105: 46136 | B105: TX104 | C105: Expense | D105: Food | E105: Dinner with study group | F105: 220 | G105: UPI | H105: =TEXT(A105,"mmm-yyyy") -> Apr-2026 | I105: =SUMIFS($F$2:F171,$C$2:C171,"Income")-SUMIFS($F$2:F171,$C$2:C171,"Expense") -> 1735 | J105: =IF(C105="Income","-",IFERROR(VLOOKUP(D105,Budget!$A$2:$F$12,6,FALSE),"-")) -> Within Budget
A106: 46137 | B106: TX105 | C106: Expense | D106: Stationery | E106: Notebooks for semester | F106: 140 | G106: UPI | H106: =TEXT(A106,"mmm-yyyy") -> Apr-2026 | I106: =SUMIFS($F$2:F171,$C$2:C171,"Income")-SUMIFS($F$2:F171,$C$2:C171,"Expense") -> 1735 | J106: =IF(C106="Income","-",IFERROR(VLOOKUP(D106,Budget!$A$2:$F$12,6,FALSE),"-")) -> Within Budget
A107: 46138 | B107: TX106 | C107: Expense | D107: Food | E107: Chai and samosa break | F107: 50 | G107: Cash | H107: =TEXT(A107,"mmm-yyyy") -> Apr-2026 | I107: =SUMIFS($F$2:F171,$C$2:C171,"Income")-SUMIFS($F$2:F171,$C$2:C171,"Expense") -> 1735 | J107: =IF(C107="Income","-",IFERROR(VLOOKUP(D107,Budget!$A$2:$F$12,6,FALSE),"-")) -> Within Budget
A108: 46139 | B108: TX107 | C108: Expense | D108: Entertainment | E108: Music app subscription | F108: 119 | G108: UPI | H108: =TEXT(A108,"mmm-yyyy") -> Apr-2026 | I108: =SUMIFS($F$2:F171,$C$2:C171,"Income")-SUMIFS($F$2:F171,$C$2:C171,"Expense") -> 1735 | J108: =IF(C108="Income","-",IFERROR(VLOOKUP(D108,Budget!$A$2:$F$12,6,FALSE),"-")) -> Near Limit
A109: 46140 | B109: TX108 | C109: Expense | D109: Gifts | E109: Farewell card & chocolate | F109: 150 | G109: Cash | H109: =TEXT(A109,"mmm-yyyy") -> Apr-2026 | I109: =SUMIFS($F$2:F171,$C$2:C171,"Income")-SUMIFS($F$2:F171,$C$2:C171,"Expense") -> 1735 | J109: =IF(C109="Income","-",IFERROR(VLOOKUP(D109,Budget!$A$2:$F$12,6,FALSE),"-")) -> Within Budget
A110: 46141 | B110: TX109 | C110: Expense | D110: Travel | E110: Bus fare | F110: 40 | G110: Cash | H110: =TEXT(A110,"mmm-yyyy") -> Apr-2026 | I110: =SUMIFS($F$2:F171,$C$2:C171,"Income")-SUMIFS($F$2:F171,$C$2:C171,"Expense") -> 1735 | J110: =IF(C110="Income","-",IFERROR(VLOOKUP(D110,Budget!$A$2:$F$12,6,FALSE),"-")) -> Within Budget
A111: 46142 | B111: TX110 | C111: Expense | D111: Food | E111: End of month dinner | F111: 160 | G111: UPI | H111: =TEXT(A111,"mmm-yyyy") -> Apr-2026 | I111: =SUMIFS($F$2:F171,$C$2:C171,"Income")-SUMIFS($F$2:F171,$C$2:C171,"Expense") -> 1735 | J111: =IF(C111="Income","-",IFERROR(VLOOKUP(D111,Budget!$A$2:$F$12,6,FALSE),"-")) -> Within Budget
A112: 46143 | B112: TX111 | C112: Income | D112: Pocket Money | E112: May monthly allowance | F112: 3500 | G112: UPI | H112: =TEXT(A112,"mmm-yyyy") -> May-2026 | I112: =SUMIFS($F$2:F171,$C$2:C171,"Income")-SUMIFS($F$2:F171,$C$2:C171,"Expense") -> 1735 | J112: =IF(C112="Income","-",IFERROR(VLOOKUP(D112,Budget!$A$2:$F$12,6,FALSE),"-")) -> -
A113: 46144 | B113: TX112 | C113: Expense | D113: Food | E113: Breakfast and tea | F113: 70 | G113: Cash | H113: =TEXT(A113,"mmm-yyyy") -> May-2026 | I113: =SUMIFS($F$2:F171,$C$2:C171,"Income")-SUMIFS($F$2:F171,$C$2:C171,"Expense") -> 1735 | J113: =IF(C113="Income","-",IFERROR(VLOOKUP(D113,Budget!$A$2:$F$12,6,FALSE),"-")) -> Within Budget
A114: 46145 | B114: TX113 | C114: Expense | D114: Travel | E114: Bus pass renewal | F114: 450 | G114: UPI | H114: =TEXT(A114,"mmm-yyyy") -> May-2026 | I114: =SUMIFS($F$2:F171,$C$2:C171,"Income")-SUMIFS($F$2:F171,$C$2:C171,"Expense") -> 1735 | J114: =IF(C114="Income","-",IFERROR(VLOOKUP(D114,Budget!$A$2:$F$12,6,FALSE),"-")) -> Within Budget
A115: 46146 | B115: TX114 | C115: Expense | D115: Education | E115: Online mock test series | F115: 350 | G115: UPI | H115: =TEXT(A115,"mmm-yyyy") -> May-2026 | I115: =SUMIFS($F$2:F171,$C$2:C171,"Income")-SUMIFS($F$2:F171,$C$2:C171,"Expense") -> 1735 | J115: =IF(C115="Income","-",IFERROR(VLOOKUP(D115,Budget!$A$2:$F$12,6,FALSE),"-")) -> Within Budget
A116: 46147 | B116: TX115 | C116: Expense | D116: Food | E116: Lunch at food court | F116: 150 | G116: UPI | H116: =TEXT(A116,"mmm-yyyy") -> May-2026 | I116: =SUMIFS($F$2:F171,$C$2:C171,"Income")-SUMIFS($F$2:F171,$C$2:C171,"Expense") -> 1735 | J116: =IF(C116="Income","-",IFERROR(VLOOKUP(D116,Budget!$A$2:$F$12,6,FALSE),"-")) -> Within Budget
A117: 46148 | B117: TX116 | C117: Expense | D117: Stationery | E117: Correction pen & markers | F117: 90 | G117: Cash | H117: =TEXT(A117,"mmm-yyyy") -> May-2026 | I117: =SUMIFS($F$2:F171,$C$2:C171,"Income")-SUMIFS($F$2:F171,$C$2:C171,"Expense") -> 1735 | J117: =IF(C117="Income","-",IFERROR(VLOOKUP(D117,Budget!$A$2:$F$12,6,FALSE),"-")) -> Within Budget
A118: 46149 | B118: TX117 | C118: Income | D118: Part-time Work | E118: Content writing gig | F118: 1200 | G118: UPI | H118: =TEXT(A118,"mmm-yyyy") -> May-2026 | I118: =SUMIFS($F$2:F171,$C$2:C171,"Income")-SUMIFS($F$2:F171,$C$2:C171,"Expense") -> 1735 | J118: =IF(C118="Income","-",IFERROR(VLOOKUP(D118,Budget!$A$2:$F$12,6,FALSE),"-")) -> -
A119: 46150 | B119: TX118 | C119: Expense | D119: Shopping | E119: Sneakers discount sale | F119: 890 | G119: UPI | H119: =TEXT(A119,"mmm-yyyy") -> May-2026 | I119: =SUMIFS($F$2:F171,$C$2:C171,"Income")-SUMIFS($F$2:F171,$C$2:C171,"Expense") -> 1735 | J119: =IF(C119="Income","-",IFERROR(VLOOKUP(D119,Budget!$A$2:$F$12,6,FALSE),"-")) -> Within Budget
A120: 46151 | B120: TX119 | C120: Expense | D120: Food | E120: Snacks with classmates | F120: 110 | G120: Cash | H120: =TEXT(A120,"mmm-yyyy") -> May-2026 | I120: =SUMIFS($F$2:F171,$C$2:C171,"Income")-SUMIFS($F$2:F171,$C$2:C171,"Expense") -> 1735 | J120: =IF(C120="Income","-",IFERROR(VLOOKUP(D120,Budget!$A$2:$F$12,6,FALSE),"-")) -> Within Budget
A121: 46152 | B121: TX120 | C121: Expense | D121: Mobile | E121: Prepaid recharge | F121: 239 | G121: UPI | H121: =TEXT(A121,"mmm-yyyy") -> May-2026 | I121: =SUMIFS($F$2:F171,$C$2:C171,"Income")-SUMIFS($F$2:F171,$C$2:C171,"Expense") -> 1735 | J121: =IF(C121="Income","-",IFERROR(VLOOKUP(D121,Budget!$A$2:$F$12,6,FALSE),"-")) -> Within Budget
A122: 46153 | B122: TX121 | C122: Expense | D122: Travel | E122: Cab fare (group split) | F122: 120 | G122: UPI | H122: =TEXT(A122,"mmm-yyyy") -> May-2026 | I122: =SUMIFS($F$2:F171,$C$2:C171,"Income")-SUMIFS($F$2:F171,$C$2:C171,"Expense") -> 1735 | J122: =IF(C122="Income","-",IFERROR(VLOOKUP(D122,Budget!$A$2:$F$12,6,FALSE),"-")) -> Within Budget
A123: 46154 | B123: TX122 | C123: Expense | D123: Food | E123: College canteen lunch | F123: 125 | G123: UPI | H123: =TEXT(A123,"mmm-yyyy") -> May-2026 | I123: =SUMIFS($F$2:F171,$C$2:C171,"Income")-SUMIFS($F$2:F171,$C$2:C171,"Expense") -> 1735 | J123: =IF(C123="Income","-",IFERROR(VLOOKUP(D123,Budget!$A$2:$F$12,6,FALSE),"-")) -> Within Budget
A124: 46155 | B124: TX123 | C124: Expense | D124: Entertainment | E124: Movie ticket (IMAX) | F124: 350 | G124: UPI | H124: =TEXT(A124,"mmm-yyyy") -> May-2026 | I124: =SUMIFS($F$2:F171,$C$2:C171,"Income")-SUMIFS($F$2:F171,$C$2:C171,"Expense") -> 1735 | J124: =IF(C124="Income","-",IFERROR(VLOOKUP(D124,Budget!$A$2:$F$12,6,FALSE),"-")) -> Near Limit
A125: 46156 | B125: TX124 | C125: Expense | D125: Personal Care | E125: Sunscreen & deodorant | F125: 240 | G125: UPI | H125: =TEXT(A125,"mmm-yyyy") -> May-2026 | I125: =SUMIFS($F$2:F171,$C$2:C171,"Income")-SUMIFS($F$2:F171,$C$2:C171,"Expense") -> 1735 | J125: =IF(C125="Income","-",IFERROR(VLOOKUP(D125,Budget!$A$2:$F$12,6,FALSE),"-")) -> Within Budget
A126: 46157 | B126: TX125 | C126: Income | D126: Pocket Money | E126: Project work allowance | F126: 500 | G126: UPI | H126: =TEXT(A126,"mmm-yyyy") -> May-2026 | I126: =SUMIFS($F$2:F171,$C$2:C171,"Income")-SUMIFS($F$2:F171,$C$2:C171,"Expense") -> 1735 | J126: =IF(C126="Income","-",IFERROR(VLOOKUP(D126,Budget!$A$2:$F$12,6,FALSE),"-")) -> -
A127: 46158 | B127: TX126 | C127: Expense | D127: Food | E127: Dinner with friends | F127: 210 | G127: UPI | H127: =TEXT(A127,"mmm-yyyy") -> May-2026 | I127: =SUMIFS($F$2:F171,$C$2:C171,"Income")-SUMIFS($F$2:F171,$C$2:C171,"Expense") -> 1735 | J127: =IF(C127="Income","-",IFERROR(VLOOKUP(D127,Budget!$A$2:$F$12,6,FALSE),"-")) -> Within Budget
A128: 46159 | B128: TX127 | C128: Expense | D128: Travel | E128: Bus fare | F128: 40 | G128: Cash | H128: =TEXT(A128,"mmm-yyyy") -> May-2026 | I128: =SUMIFS($F$2:F171,$C$2:C171,"Income")-SUMIFS($F$2:F171,$C$2:C171,"Expense") -> 1735 | J128: =IF(C128="Income","-",IFERROR(VLOOKUP(D128,Budget!$A$2:$F$12,6,FALSE),"-")) -> Within Budget
A129: 46160 | B129: TX128 | C129: Expense | D129: Health | E129: Dental checkup & paste | F129: 280 | G129: UPI | H129: =TEXT(A129,"mmm-yyyy") -> May-2026 | I129: =SUMIFS($F$2:F171,$C$2:C171,"Income")-SUMIFS($F$2:F171,$C$2:C171,"Expense") -> 1735 | J129: =IF(C129="Income","-",IFERROR(VLOOKUP(D129,Budget!$A$2:$F$12,6,FALSE),"-")) -> Within Budget
A130: 46161 | B130: TX129 | C130: Expense | D130: Food | E130: Juice and snacks | F130: 85 | G130: Cash | H130: =TEXT(A130,"mmm-yyyy") -> May-2026 | I130: =SUMIFS($F$2:F171,$C$2:C171,"Income")-SUMIFS($F$2:F171,$C$2:C171,"Expense") -> 1735 | J130: =IF(C130="Income","-",IFERROR(VLOOKUP(D130,Budget!$A$2:$F$12,6,FALSE),"-")) -> Within Budget
A131: 46162 | B131: TX130 | C131: Expense | D131: Education | E131: Reference textbook | F131: 380 | G131: UPI | H131: =TEXT(A131,"mmm-yyyy") -> May-2026 | I131: =SUMIFS($F$2:F171,$C$2:C171,"Income")-SUMIFS($F$2:F171,$C$2:C171,"Expense") -> 1735 | J131: =IF(C131="Income","-",IFERROR(VLOOKUP(D131,Budget!$A$2:$F$12,6,FALSE),"-")) -> Within Budget
A132: 46163 | B132: TX131 | C132: Expense | D132: Travel | E132: Auto fare | F132: 80 | G132: Cash | H132: =TEXT(A132,"mmm-yyyy") -> May-2026 | I132: =SUMIFS($F$2:F171,$C$2:C171,"Income")-SUMIFS($F$2:F171,$C$2:C171,"Expense") -> 1735 | J132: =IF(C132="Income","-",IFERROR(VLOOKUP(D132,Budget!$A$2:$F$12,6,FALSE),"-")) -> Within Budget
A133: 46164 | B133: TX132 | C133: Expense | D133: Food | E133: Campus cafe lunch | F133: 140 | G133: UPI | H133: =TEXT(A133,"mmm-yyyy") -> May-2026 | I133: =SUMIFS($F$2:F171,$C$2:C171,"Income")-SUMIFS($F$2:F171,$C$2:C171,"Expense") -> 1735 | J133: =IF(C133="Income","-",IFERROR(VLOOKUP(D133,Budget!$A$2:$F$12,6,FALSE),"-")) -> Within Budget
A134: 46165 | B134: TX133 | C134: Expense | D134: Shopping | E134: Backpack repair & strap | F134: 180 | G134: Cash | H134: =TEXT(A134,"mmm-yyyy") -> May-2026 | I134: =SUMIFS($F$2:F171,$C$2:C171,"Income")-SUMIFS($F$2:F171,$C$2:C171,"Expense") -> 1735 | J134: =IF(C134="Income","-",IFERROR(VLOOKUP(D134,Budget!$A$2:$F$12,6,FALSE),"-")) -> Within Budget
A135: 46166 | B135: TX134 | C135: Expense | D135: Entertainment | E135: Gaming cafe with buddies | F135: 200 | G135: UPI | H135: =TEXT(A135,"mmm-yyyy") -> May-2026 | I135: =SUMIFS($F$2:F171,$C$2:C171,"Income")-SUMIFS($F$2:F171,$C$2:C171,"Expense") -> 1735 | J135: =IF(C135="Income","-",IFERROR(VLOOKUP(D135,Budget!$A$2:$F$12,6,FALSE),"-")) -> Near Limit
A136: 46167 | B136: TX135 | C136: Income | D136: Savings Interest | E136: Monthly interest credit | F136: 38 | G136: Bank | H136: =TEXT(A136,"mmm-yyyy") -> May-2026 | I136: =SUMIFS($F$2:F171,$C$2:C171,"Income")-SUMIFS($F$2:F171,$C$2:C171,"Expense") -> 1735 | J136: =IF(C136="Income","-",IFERROR(VLOOKUP(D136,Budget!$A$2:$F$12,6,FALSE),"-")) -> -
A137: 46168 | B137: TX136 | C137: Expense | D137: Food | E137: Evening street food | F137: 90 | G137: Cash | H137: =TEXT(A137,"mmm-yyyy") -> May-2026 | I137: =SUMIFS($F$2:F171,$C$2:C171,"Income")-SUMIFS($F$2:F171,$C$2:C171,"Expense") -> 1735 | J137: =IF(C137="Income","-",IFERROR(VLOOKUP(D137,Budget!$A$2:$F$12,6,FALSE),"-")) -> Within Budget
A138: 46169 | B138: TX137 | C138: Expense | D138: Travel | E138: Bus fare | F138: 40 | G138: Cash | H138: =TEXT(A138,"mmm-yyyy") -> May-2026 | I138: =SUMIFS($F$2:F171,$C$2:C171,"Income")-SUMIFS($F$2:F171,$C$2:C171,"Expense") -> 1735 | J138: =IF(C138="Income","-",IFERROR(VLOOKUP(D138,Budget!$A$2:$F$12,6,FALSE),"-")) -> Within Budget
A139: 46170 | B139: TX138 | C139: Expense | D139: Gifts | E139: Mother's Day token gift | F139: 320 | G139: UPI | H139: =TEXT(A139,"mmm-yyyy") -> May-2026 | I139: =SUMIFS($F$2:F171,$C$2:C171,"Income")-SUMIFS($F$2:F171,$C$2:C171,"Expense") -> 1735 | J139: =IF(C139="Income","-",IFERROR(VLOOKUP(D139,Budget!$A$2:$F$12,6,FALSE),"-")) -> Within Budget
A140: 46171 | B140: TX139 | C140: Expense | D140: Other | E140: College ID card re-issue | F140: 100 | G140: UPI | H140: =TEXT(A140,"mmm-yyyy") -> May-2026 | I140: =SUMIFS($F$2:F171,$C$2:C171,"Income")-SUMIFS($F$2:F171,$C$2:C171,"Expense") -> 1735 | J140: =IF(C140="Income","-",IFERROR(VLOOKUP(D140,Budget!$A$2:$F$12,6,FALSE),"-")) -> Within Budget
A141: 46172 | B141: TX140 | C141: Expense | D141: Food | E141: Dinner celebration | F141: 195 | G141: UPI | H141: =TEXT(A141,"mmm-yyyy") -> May-2026 | I141: =SUMIFS($F$2:F171,$C$2:C171,"Income")-SUMIFS($F$2:F171,$C$2:C171,"Expense") -> 1735 | J141: =IF(C141="Income","-",IFERROR(VLOOKUP(D141,Budget!$A$2:$F$12,6,FALSE),"-")) -> Within Budget
A142: 46174 | B142: TX141 | C142: Income | D142: Pocket Money | E142: June monthly allowance | F142: 3500 | G142: UPI | H142: =TEXT(A142,"mmm-yyyy") -> Jun-2026 | I142: =SUMIFS($F$2:F171,$C$2:C171,"Income")-SUMIFS($F$2:F171,$C$2:C171,"Expense") -> 1735 | J142: =IF(C142="Income","-",IFERROR(VLOOKUP(D142,Budget!$A$2:$F$12,6,FALSE),"-")) -> -
A143: 46175 | B143: TX142 | C143: Expense | D143: Food | E143: Breakfast and fruit juice | F143: 80 | G143: Cash | H143: =TEXT(A143,"mmm-yyyy") -> Jun-2026 | I143: =SUMIFS($F$2:F171,$C$2:C171,"Income")-SUMIFS($F$2:F171,$C$2:C171,"Expense") -> 1735 | J143: =IF(C143="Income","-",IFERROR(VLOOKUP(D143,Budget!$A$2:$F$12,6,FALSE),"-")) -> Within Budget
A144: 46176 | B144: TX143 | C144: Expense | D144: Travel | E144: Metro card smart recharge | F144: 300 | G144: UPI | H144: =TEXT(A144,"mmm-yyyy") -> Jun-2026 | I144: =SUMIFS($F$2:F171,$C$2:C171,"Income")-SUMIFS($F$2:F171,$C$2:C171,"Expense") -> 1735 | J144: =IF(C144="Income","-",IFERROR(VLOOKUP(D144,Budget!$A$2:$F$12,6,FALSE),"-")) -> Within Budget
A145: 46177 | B145: TX144 | C145: Expense | D145: Food | E145: College lunch | F145: 130 | G145: UPI | H145: =TEXT(A145,"mmm-yyyy") -> Jun-2026 | I145: =SUMIFS($F$2:F171,$C$2:C171,"Income")-SUMIFS($F$2:F171,$C$2:C171,"Expense") -> 1735 | J145: =IF(C145="Income","-",IFERROR(VLOOKUP(D145,Budget!$A$2:$F$12,6,FALSE),"-")) -> Within Budget
A146: 46178 | B146: TX145 | C146: Expense | D146: Stationery | E146: Drafting tools and paper | F146: 160 | G146: UPI | H146: =TEXT(A146,"mmm-yyyy") -> Jun-2026 | I146: =SUMIFS($F$2:F171,$C$2:C171,"Income")-SUMIFS($F$2:F171,$C$2:C171,"Expense") -> 1735 | J146: =IF(C146="Income","-",IFERROR(VLOOKUP(D146,Budget!$A$2:$F$12,6,FALSE),"-")) -> Within Budget
...

Sheet Budget
A1: Category | B1: Monthly Budget | C1: Actual Spending | D1: Remaining Budget | E1: Budget Usage (%) | F1: Status
A2: Food | B2: 1800 | C2: =SUMIFS(Transactions!$F:$F,Transactions!$D:$D,$A2,Transactions!$C:$C,"Expense",Transactions!$A:$A,">="&Dashboard!$B$2,Transactions!$A:$A,"<"&EDATE(Dashboard!$B$2,1)) -> 1285 | D2: =B2-C2 -> 515 | E2: =IFERROR(C2/B2,0) -> 0.71388889 | F2: =IF(C2>B2,"Over Budget",IF(C2>=B2*0.8,"Near Limit","Within Budget")) -> Within Budget
A3: Travel | B3: 800 | C3: =SUMIFS(Transactions!$F:$F,Transactions!$D:$D,$A3,Transactions!$C:$C,"Expense",Transactions!$A:$A,">="&Dashboard!$B$2,Transactions!$A:$A,"<"&EDATE(Dashboard!$B$2,1)) -> 390 | D3: =B3-C3 -> 410 | E3: =IFERROR(C3/B3,0) -> 0.4875 | F3: =IF(C3>B3,"Over Budget",IF(C3>=B3*0.8,"Near Limit","Within Budget")) -> Within Budget
A4: Stationery | B4: 500 | C4: =SUMIFS(Transactions!$F:$F,Transactions!$D:$D,$A4,Transactions!$C:$C,"Expense",Transactions!$A:$A,">="&Dashboard!$B$2,Transactions!$A:$A,"<"&EDATE(Dashboard!$B$2,1)) -> 180 | D4: =B4-C4 -> 320 | E4: =IFERROR(C4/B4,0) -> 0.36 | F4: =IF(C4>B4,"Over Budget",IF(C4>=B4*0.8,"Near Limit","Within Budget")) -> Within Budget
A5: Education | B5: 600 | C5: =SUMIFS(Transactions!$F:$F,Transactions!$D:$D,$A5,Transactions!$C:$C,"Expense",Transactions!$A:$A,">="&Dashboard!$B$2,Transactions!$A:$A,"<"&EDATE(Dashboard!$B$2,1)) -> 255 | D5: =B5-C5 -> 345 | E5: =IFERROR(C5/B5,0) -> 0.425 | F5: =IF(C5>B5,"Over Budget",IF(C5>=B5*0.8,"Near Limit","Within Budget")) -> Within Budget
A6: Entertainment | B6: 700 | C6: =SUMIFS(Transactions!$F:$F,Transactions!$D:$D,$A6,Transactions!$C:$C,"Expense",Transactions!$A:$A,">="&Dashboard!$B$2,Transactions!$A:$A,"<"&EDATE(Dashboard!$B$2,1)) -> 568 | D6: =B6-C6 -> 132 | E6: =IFERROR(C6/B6,0) -> 0.81142857 | F6: =IF(C6>B6,"Over Budget",IF(C6>=B6*0.8,"Near Limit","Within Budget")) -> Near Limit
A7: Mobile | B7: 300 | C7: =SUMIFS(Transactions!$F:$F,Transactions!$D:$D,$A7,Transactions!$C:$C,"Expense",Transactions!$A:$A,">="&Dashboard!$B$2,Transactions!$A:$A,"<"&EDATE(Dashboard!$B$2,1)) -> 239 | D7: =B7-C7 -> 61 | E7: =IFERROR(C7/B7,0) -> 0.79666667 | F7: =IF(C7>B7,"Over Budget",IF(C7>=B7*0.8,"Near Limit","Within Budget")) -> Within Budget
A8: Shopping | B8: 1000 | C8: =SUMIFS(Transactions!$F:$F,Transactions!$D:$D,$A8,Transactions!$C:$C,"Expense",Transactions!$A:$A,">="&Dashboard!$B$2,Transactions!$A:$A,"<"&EDATE(Dashboard!$B$2,1)) -> 750 | D8: =B8-C8 -> 250 | E8: =IFERROR(C8/B8,0) -> 0.75 | F8: =IF(C8>B8,"Over Budget",IF(C8>=B8*0.8,"Near Limit","Within Budget")) -> Within Budget
A9: Personal Care | B9: 400 | C9: =SUMIFS(Transactions!$F:$F,Transactions!$D:$D,$A9,Transactions!$C:$C,"Expense",Transactions!$A:$A,">="&Dashboard!$B$2,Transactions!$A:$A,"<"&EDATE(Dashboard!$B$2,1)) -> 220 | D9: =B9-C9 -> 180 | E9: =IFERROR(C9/B9,0) -> 0.55 | F9: =IF(C9>B9,"Over Budget",IF(C9>=B9*0.8,"Near Limit","Within Budget")) -> Within Budget
A10: Health | B10: 300 | C10: =SUMIFS(Transactions!$F:$F,Transactions!$D:$D,$A10,Transactions!$C:$C,"Expense",Transactions!$A:$A,">="&Dashboard!$B$2,Transactions!$A:$A,"<"&EDATE(Dashboard!$B$2,1)) -> 0 | D10: =B10-C10 -> 300 | E10: =IFERROR(C10/B10,0) -> 0 | F10: =IF(C10>B10,"Over Budget",IF(C10>=B10*0.8,"Near Limit","Within Budget")) -> Within Budget
A11: Gifts | B11: 300 | C11: =SUMIFS(Transactions!$F:$F,Transactions!$D:$D,$A11,Transactions!$C:$C,"Expense",Transactions!$A:$A,">="&Dashboard!$B$2,Transactions!$A:$A,"<"&EDATE(Dashboard!$B$2,1)) -> 0 | D11: =B11-C11 -> 300 | E11: =IFERROR(C11/B11,0) -> 0 | F11: =IF(C11>B11,"Over Budget",IF(C11>=B11*0.8,"Near Limit","Within Budget")) -> Within Budget
A12: Other | B12: 300 | C12: =SUMIFS(Transactions!$F:$F,Transactions!$D:$D,$A12,Transactions!$C:$C,"Expense",Transactions!$A:$A,">="&Dashboard!$B$2,Transactions!$A:$A,"<"&EDATE(Dashboard!$B$2,1)) -> 0 | D12: =B12-C12 -> 300 | E12: =IFERROR(C12/B12,0) -> 0 | F12: =IF(C12>B12,"Over Budget",IF(C12>=B12*0.8,"Near Limit","Within Budget")) -> Within Budget
A13: Total | B13: =SUM(B2:B12) -> 7000 | C13: =SUM(C2:C12) -> 3887 | D13: =B13-C13 -> 3113 | E13: =IFERROR(C13/B13,0) -> 0.55528571 | F13: =IF(C13>B13,"Over Budget",IF(C13>=B13*0.8,"Near Limit","Within Budget")) -> Within Budget

Sheet Monthly Summary
A1: Month | B1: Total Income | C1: Total Expenses | D1: Net Savings | E1: Savings Rate | F1: Transaction Count | G1: Expense Change
A2: 46023 | B2: =SUMIFS(Transactions!$F:$F,Transactions!$C:$C,"Income",Transactions!$A:$A,">="&$A2,Transactions!$A:$A,"<"&EDATE($A2,1)) -> 4035 | C2: =SUMIFS(Transactions!$F:$F,Transactions!$C:$C,"Expense",Transactions!$A:$A,">="&$A2,Transactions!$A:$A,"<"&EDATE($A2,1)) -> 3887 | D2: =B2-C2 -> 148 | E2: =IFERROR(D2/B2,0) -> 0.036679058 | F2: =COUNTIFS(Transactions!$A:$A,">="&$A2,Transactions!$A:$A,"<"&EDATE($A2,1)) -> 30 | G2: 0
A3: =EDATE(A2,1) -> 46054 | B3: =SUMIFS(Transactions!$F:$F,Transactions!$C:$C,"Income",Transactions!$A:$A,">="&$A3,Transactions!$A:$A,"<"&EDATE($A3,1)) -> 4000 | C3: =SUMIFS(Transactions!$F:$F,Transactions!$C:$C,"Expense",Transactions!$A:$A,">="&$A3,Transactions!$A:$A,"<"&EDATE($A3,1)) -> 3489 | D3: =B3-C3 -> 511 | E3: =IFERROR(D3/B3,0) -> 0.12775 | F3: =COUNTIFS(Transactions!$A:$A,">="&$A3,Transactions!$A:$A,"<"&EDATE($A3,1)) -> 20 | G3: =IF(OR(C3=0,C2=0),0,IFERROR((C3-C2)/C2,0)) -> -0.10239259
A4: =EDATE(A3,1) -> 46082 | B4: =SUMIFS(Transactions!$F:$F,Transactions!$C:$C,"Income",Transactions!$A:$A,">="&$A4,Transactions!$A:$A,"<"&EDATE($A4,1)) -> 4342 | C4: =SUMIFS(Transactions!$F:$F,Transactions!$C:$C,"Expense",Transactions!$A:$A,">="&$A4,Transactions!$A:$A,"<"&EDATE($A4,1)) -> 4253 | D4: =B4-C4 -> 89 | E4: =IFERROR(D4/B4,0) -> 0.020497467 | F4: =COUNTIFS(Transactions!$A:$A,">="&$A4,Transactions!$A:$A,"<"&EDATE($A4,1)) -> 30 | G4: =IF(OR(C4=0,C3=0),0,IFERROR((C4-C3)/C3,0)) -> 0.21897392
A5: =EDATE(A4,1) -> 46113 | B5: =SUMIFS(Transactions!$F:$F,Transactions!$C:$C,"Income",Transactions!$A:$A,">="&$A5,Transactions!$A:$A,"<"&EDATE($A5,1)) -> 5000 | C5: =SUMIFS(Transactions!$F:$F,Transactions!$C:$C,"Expense",Transactions!$A:$A,">="&$A5,Transactions!$A:$A,"<"&EDATE($A5,1)) -> 4570 | D5: =B5-C5 -> 430 | E5: =IFERROR(D5/B5,0) -> 0.086 | F5: =COUNTIFS(Transactions!$A:$A,">="&$A5,Transactions!$A:$A,"<"&EDATE($A5,1)) -> 30 | G5: =IF(OR(C5=0,C4=0),0,IFERROR((C5-C4)/C4,0)) -> 0.074535622
A6: =EDATE(A5,1) -> 46143 | B6: =SUMIFS(Transactions!$F:$F,Transactions!$C:$C,"Income",Transactions!$A:$A,">="&$A6,Transactions!$A:$A,"<"&EDATE($A6,1)) -> 5238 | C6: =SUMIFS(Transactions!$F:$F,Transactions!$C:$C,"Expense",Transactions!$A:$A,">="&$A6,Transactions!$A:$A,"<"&EDATE($A6,1)) -> 5524 | D6: =B6-C6 -> -286 | E6: =IFERROR(D6/B6,0) -> -0.054600993 | F6: =COUNTIFS(Transactions!$A:$A,">="&$A6,Transactions!$A:$A,"<"&EDATE($A6,1)) -> 30 | G6: =IF(OR(C6=0,C5=0),0,IFERROR((C6-C5)/C5,0)) -> 0.20875274
A7: =EDATE(A6,1) -> 46174 | B7: =SUMIFS(Transactions!$F:$F,Transactions!$C:$C,"Income",Transactions!$A:$A,">="&$A7,Transactions!$A:$A,"<"&EDATE($A7,1)) -> 6045 | C7: =SUMIFS(Transactions!$F:$F,Transactions!$C:$C,"Expense",Transactions!$A:$A,">="&$A7,Transactions!$A:$A,"<"&EDATE($A7,1)) -> 5202 | D7: =B7-C7 -> 843 | E7: =IFERROR(D7/B7,0) -> 0.13945409 | F7: =COUNTIFS(Transactions!$A:$A,">="&$A7,Transactions!$A:$A,"<"&EDATE($A7,1)) -> 30 | G7: =IF(OR(C7=0,C6=0),0,IFERROR((C7-C6)/C6,0)) -> -0.058291093
A8: =EDATE(A7,1) -> 46204 | B8: =SUMIFS(Transactions!$F:$F,Transactions!$C:$C,"Income",Transactions!$A:$A,">="&$A8,Transactions!$A:$A,"<"&EDATE($A8,1)) -> 0 | C8: =SUMIFS(Transactions!$F:$F,Transactions!$C:$C,"Expense",Transactions!$A:$A,">="&$A8,Transactions!$A:$A,"<"&EDATE($A8,1)) -> 0 | D8: =B8-C8 -> 0 | E8: =IFERROR(D8/B8,0) -> 0 | F8: =COUNTIFS(Transactions!$A:$A,">="&$A8,Transactions!$A:$A,"<"&EDATE($A8,1)) -> 0 | G8: =IF(OR(C8=0,C7=0),0,IFERROR((C8-C7)/C7,0)) -> 0
A9: =EDATE(A8,1) -> 46235 | B9: =SUMIFS(Transactions!$F:$F,Transactions!$C:$C,"Income",Transactions!$A:$A,">="&$A9,Transactions!$A:$A,"<"&EDATE($A9,1)) -> 0 | C9: =SUMIFS(Transactions!$F:$F,Transactions!$C:$C,"Expense",Transactions!$A:$A,">="&$A9,Transactions!$A:$A,"<"&EDATE($A9,1)) -> 0 | D9: =B9-C9 -> 0 | E9: =IFERROR(D9/B9,0) -> 0 | F9: =COUNTIFS(Transactions!$A:$A,">="&$A9,Transactions!$A:$A,"<"&EDATE($A9,1)) -> 0 | G9: =IF(OR(C9=0,C8=0),0,IFERROR((C9-C8)/C8,0)) -> 0
A10: =EDATE(A9,1) -> 46266 | B10: =SUMIFS(Transactions!$F:$F,Transactions!$C:$C,"Income",Transactions!$A:$A,">="&$A10,Transactions!$A:$A,"<"&EDATE($A10,1)) -> 0 | C10: =SUMIFS(Transactions!$F:$F,Transactions!$C:$C,"Expense",Transactions!$A:$A,">="&$A10,Transactions!$A:$A,"<"&EDATE($A10,1)) -> 0 | D10: =B10-C10 -> 0 | E10: =IFERROR(D10/B10,0) -> 0 | F10: =COUNTIFS(Transactions!$A:$A,">="&$A10,Transactions!$A:$A,"<"&EDATE($A10,1)) -> 0 | G10: =IF(OR(C10=0,C9=0),0,IFERROR((C10-C9)/C9,0)) -> 0
A11: =EDATE(A10,1) -> 46296 | B11: =SUMIFS(Transactions!$F:$F,Transactions!$C:$C,"Income",Transactions!$A:$A,">="&$A11,Transactions!$A:$A,"<"&EDATE($A11,1)) -> 0 | C11: =SUMIFS(Transactions!$F:$F,Transactions!$C:$C,"Expense",Transactions!$A:$A,">="&$A11,Transactions!$A:$A,"<"&EDATE($A11,1)) -> 0 | D11: =B11-C11 -> 0 | E11: =IFERROR(D11/B11,0) -> 0 | F11: =COUNTIFS(Transactions!$A:$A,">="&$A11,Transactions!$A:$A,"<"&EDATE($A11,1)) -> 0 | G11: =IF(OR(C11=0,C10=0),0,IFERROR((C11-C10)/C10,0)) -> 0
A12: =EDATE(A11,1) -> 46327 | B12: =SUMIFS(Transactions!$F:$F,Transactions!$C:$C,"Income",Transactions!$A:$A,">="&$A12,Transactions!$A:$A,"<"&EDATE($A12,1)) -> 0 | C12: =SUMIFS(Transactions!$F:$F,Transactions!$C:$C,"Expense",Transactions!$A:$A,">="&$A12,Transactions!$A:$A,"<"&EDATE($A12,1)) -> 0 | D12: =B12-C12 -> 0 | E12: =IFERROR(D12/B12,0) -> 0 | F12: =COUNTIFS(Transactions!$A:$A,">="&$A12,Transactions!$A:$A,"<"&EDATE($A12,1)) -> 0 | G12: =IF(OR(C12=0,C11=0),0,IFERROR((C12-C11)/C11,0)) -> 0
A13: =EDATE(A12,1) -> 46357 | B13: =SUMIFS(Transactions!$F:$F,Transactions!$C:$C,"Income",Transactions!$A:$A,">="&$A13,Transactions!$A:$A,"<"&EDATE($A13,1)) -> 0 | C13: =SUMIFS(Transactions!$F:$F,Transactions!$C:$C,"Expense",Transactions!$A:$A,">="&$A13,Transactions!$A:$A,"<"&EDATE($A13,1)) -> 0 | D13: =B13-C13 -> 0 | E13: =IFERROR(D13/B13,0) -> 0 | F13: =COUNTIFS(Transactions!$A:$A,">="&$A13,Transactions!$A:$A,"<"&EDATE($A13,1)) -> 0 | G13: =IF(OR(C13=0,C12=0),0,IFERROR((C13-C12)/C12,0)) -> 0
A14: Total / Average | B14: =SUM(B2:B13) -> 28660 | C14: =SUM(C2:C13) -> 26925 | D14: =SUM(D2:D13) -> 1735 | E14: =IFERROR(D14/B14,0) -> 0.060537334 | F14: =SUM(F2:F13) -> 170 | G14: -

Sheet Savings Goals
A1: POCKET MONEY SAVINGS GOALS TRACKER
B3: TOTAL TARGET | D3: TOTAL SAVED | F3: OVERALL PROGRESS | H3: REMAINING AMOUNT
B4: =SUM(D7:D11) -> 17000 | D4: =SUM(E7:E11) -> 10300 | F4: =IFERROR(D4/B4,0) -> 0.60588235 | H4: =B4-D4 -> 6700
A6: Goal ID | B6: Goal Name | C6: Category | D6: Target Amount | E6: Current Saved | F6: Monthly Target | G6: Target Date | H6: Progress (%) | I6: Remaining | J6: Status
A7: SG01 | B7: Emergency Fund (3 Months) | C7: Financial Safety | D7: 5000 | E7: 3500 | F7: 500 | G7: 46203 | H7: =E7/D7 -> 0.7 | I7: =D7-E7 -> 1500 | J7: =IF(H7>=1,"Achieved",IF(H7>=0.7,"On Track",IF(H7>=0.4,"In Progress","Needs Attention"))) -> On Track
A8: SG02 | B8: Noise-Cancelling Headphones | C8: Tech & Gadgets | D8: 3500 | E8: 2800 | F8: 700 | G8: 46127 | H8: =E8/D8 -> 0.8 | I8: =D8-E8 -> 700 | J8: =IF(H8>=1,"Achieved",IF(H8>=0.7,"On Track",IF(H8>=0.4,"In Progress","Needs Attention"))) -> On Track
A9: SG03 | B9: College Tech Fest Trip | C9: Travel & Events | D9: 4000 | E9: 1600 | F9: 800 | G9: 46162 | H9: =E9/D9 -> 0.4 | I9: =D9-E9 -> 2400 | J9: =IF(H9>=1,"Achieved",IF(H9>=0.7,"On Track",IF(H9>=0.4,"In Progress","Needs Attention"))) -> In Progress
A10: SG04 | B10: Data Science & AI Course | C10: Skill Building | D10: 2500 | E10: 1000 | F10: 300 | G10: 46265 | H10: =E10/D10 -> 0.4 | I10: =D10-E10 -> 1500 | J10: =IF(H10>=1,"Achieved",IF(H10>=0.7,"On Track",IF(H10>=0.4,"In Progress","Needs Attention"))) -> In Progress
A11: SG05 | B11: Mom's Birthday Gift | C11: Family & Gifts | D11: 2000 | E11: 1400 | F11: 300 | G11: 46213 | H11: =E11/D11 -> 0.7 | I11: =D11-E11 -> 600 | J11: =IF(H11>=1,"Achieved",IF(H11>=0.7,"On Track",IF(H11>=0.4,"In Progress","Needs Attention"))) -> On Track
B12: Total | D12: =SUM(D7:D11) -> 17000 | E12: =SUM(E7:E11) -> 10300 | F12: =SUM(F7:F11) -> 2600 | H12: =IFERROR(E12/D12,0) -> 0.60588235 | I12: =SUM(I7:I11) -> 6700

Sheet Categories
A1: Category | B1: Type
A2: Pocket Money | B2: Income
A3: Gift | B3: Income
A4: Part-time Work | B4: Income
A5: Savings Interest | B5: Income
A6: Food | B6: Expense
A7: Travel | B7: Expense
A8: Stationery | B8: Expense
A9: Education | B9: Expense
A10: Entertainment | B10: Expense
A11: Mobile | B11: Expense
A12: Shopping | B12: Expense
... A16: Other | B16: Expense
